apksearch/__init__.py
apksearch/__main__.py
apksearch/cli.py
apksearch/sites/__init__.py
apksearch/sites/apkad.py
apksearch/sites/apkcombo.py
apksearch/sites/apkfab.py
apksearch/sites/apkmirror.py
apksearch/sites/apkpure.py
apksearch/sites/appteka.py
apksearch/sites/aptoide.py
apksearch-1.3.1.dist-info/licenses/LICENSE
apksearch-1.3.1.dist-info/METADATA
apksearch-1.3.1.dist-info/WHEEL
apksearch-1.3.1.dist-info/entry_points.txt
apksearch-1.3.1.dist-info/top_level.txt
apksearch-1.3.1.dist-info/RECORD
