Metadata-Version: 2.4
Name: apksearch
Version: 1.3.1
Summary: Search for apks on varius websites
Author-email: Abhi <allinoneallinone00@gmail.com>
License: MIT License
Project-URL: homepage, https://github.com/AbhiTheModder/apksearch.git
Project-URL: source, https://github.com/AbhiTheModder/apksearch.git
Project-URL: issues, https://github.com/AbhiTheModder/apksearch.git/issues
Classifier: Development Status :: 5 - Production/Stable
Classifier: Natural Language :: English
Classifier: Intended Audience :: Developers
Classifier: License :: OSI Approved :: MIT License
Classifier: Programming Language :: Python :: 3
Classifier: Programming Language :: Python :: 3.10
Classifier: Programming Language :: Python :: 3.11
Classifier: Programming Language :: Python :: 3.12
Classifier: Topic :: Software Development :: Libraries :: Python Modules
Classifier: Topic :: Text Processing :: General
Classifier: Topic :: Utilities
Classifier: Operating System :: OS Independent
Requires-Python: >=3.10
License-File: LICENSE
Requires-Dist: beautifulsoup4>=4.12.3
Requires-Dist: requests>=2.32.3
Provides-Extra: dev
Requires-Dist: pytest>=7.4.3; extra == "dev"
Requires-Dist: black>=23.12.1; extra == "dev"
Requires-Dist: flake8>=6.1.0; extra == "dev"
Dynamic: license-file
